README.rst
setup.py
./pipinator/website/static/mountains-big.jpg
./pipinator/website/static/mountains-big.jpg.100x100_q85_crop.jpg
./pipinator/website/templates/index.html
pipinator/__main__.py
pipinator/manage.py
pipinator/settings.py
pipinator/urls.py
pipinator/wsgi.py
pipinator.egg-info/PKG-INFO
pipinator.egg-info/SOURCES.txt
pipinator.egg-info/dependency_links.txt
pipinator.egg-info/entry_points.txt
pipinator.egg-info/requires.txt
pipinator.egg-info/top_level.txt
pipinator/website/__init__.py
pipinator/website/admin.py
pipinator/website/apps.py
pipinator/website/models.py
pipinator/website/tests.py
pipinator/website/urls.py
pipinator/website/views.py
pipinator/website/templates/index.html