Metadata-Version: 1.1
Name: pipinator
Version: 0.1.20
Summary: Example Project to show how to package a Django project for pip and PyPI
Home-page: https://github.com/antonpirker/django-pip-project
Author: Anton Pirker
Author-email: anton@ignaz.at
License: UNKNOWN
Keywords: django
Platform: UNKNOWN
Classifier: Operating System :: POSIX :: Linux
Classifier: Programming Language :: Python :: 3 :: Only
Classifier: Programming Language :: Python :: 3.4
Classifier: Programming Language :: Python :: 3.5
Classifier: Programming Language :: Python :: 3.6
Classifier: License :: OSI Approved :: MIT License
